src/测试/delay_wakeup.v
module delay_wakeup(
	input wire clk,
	input wire rst,
	input wire issu_en,
    input wire [7:0] wdy,
    output reg valid
    );
reg [7:0] shift_reg;
always @(posedge clk)
begin
	if(!rst)
	begin
		valid <= 1'b0;
		shift_reg <= 8'b00000000;
	end
	else if(issu_en)
	begin
		shift_reg <= wdy;
		valid <= 1'b0;
	end
end
always @(posedge clk)
begin
	if(shift_reg[0] != 1'b1)
	begin
		shift_reg <= shift_reg>>1;
		valid <= 1'b0;
	end
	else if(shift_reg[0] == 1'b1)
	begin
		shift_reg <= 8'b00000000;
		valid <= 1'b1;
	end
end
endmodule

src/测试/tb_test.v
`include "./delay_wakeup.v"
module tb_test ();
	reg clk;   
	reg rst;
	reg issu_en;
	reg [7:0] wdy;
	wire valid;
always #10 clk = ~clk;

delay_wakeup uut(
	.clk(clk),
	.rst(rst),
	.wdy(wdy),
	.issu_en(issu_en),
	.valid(valid)
	);
initial
begin
	clk = 1;
	rst = 1;
	wdy = 8'd0;
	#20
	rst = 0;
	#10
	rst = 1;
	#10
	issu_en = 1;
	wdy = 8'b11111000;
	#20 issu_en = 0;
	#1000 $finish;
end
  initial
     begin
			$dumpfile ("tb_test.vcd");
            $dumpvars (0,tb_test);
     end 


endmodule

src/测试/tb_test.vcd
$date
	Wed Dec 25 10:24:45 2019
$end
$version
	Icarus Verilog
$end
$timescale
	1s
$end
$scope module tb_test $end
$var wire 1 ! valid $end
$var reg 1 " clk $end
$var reg 1 # issu_en $end
$var reg 1 $ rst $end
$var reg 8 % wdy [7:0] $end
$scope module uut $end
$var wire 1 & clk $end
$var wire 1 ' issu_en $end
$var wire 1 ( rst $end
$var wire 8 ) wdy [7:0] $end
$var reg 8 * shift_reg [7:0] $end
$var reg 1 + valid $end
$upscope $end
$upscope $end
$enddefinitions $end
#0
$dumpvars
x+
bx *
b0 )
1(
x'
1&
b0 %
1$
x#
1"
x!
$end
#10
0"
0&
#20
b0 *
0+
0!
1"
1&
0$
0(
#30
0"
0&
1$
1(
#40
b11111000 *
1"
1&
b11111000 %
b11111000 )
1#
1'
#50
0"
0&
#60
b1111100 *
1"
1&
0#
0'
#70
0"
0&
#80
b111110 *
1"
1&
#90
0"
0&
#100
b11111 *
1"
1&
#110
0"
0&
#120
1+
1!
b0 *
1"
1&
#130
0"
0&
#140
0+
0!
1"
1&
